setup.py
crypx.egg-info/PKG-INFO
crypx.egg-info/SOURCES.txt
crypx.egg-info/dependency_links.txt
crypx.egg-info/top_level.txt
tc4/__init__.py