Metadata-Version: 2.1
Name: crypx
Version: 0.1
Summary: A powerful encryption libraries in Python created by the ASH team
Home-page: UNKNOWN
Author: ASH team
License: UNKNOWN
Platform: UNKNOWN
